{
  "manifestVersion": "3.2",
  "admin": {
    "address": "0x5e5b7D871efDE8224390a334045e1dcb7daAf4E2",
    "txHash": "0x9fd8c71749cc3ef6ffe853166fad130a7d827c91c3c36c43bf1c4af8fde55843"
  },
  "proxies": [
    {
      "address": "0xDF9BF58Aa1A1B73F0e214d79C652a7dd37a6074e",
      "txHash": "0xe510ac44c4df9830b42bebb9ac0423f5750892e28116dd163f8ba29593fd19a6",
      "kind": "transparent"
    },
    {
      "address": "0xd07D54b0231088Ca9BF7DA6291c911B885cBC140",
      "txHash": "0xb7d0192d551e0ecee76d53e00596e619491bae6fb2a12bfdf5e7d65a51fe23e4",
      "kind": "transparent"
    },
    {
      "address": "0x2AFA4bE0f2468347A2F086c2167630fb1E58b725",
      "txHash": "0x1eb58ac066b33a347d9e5a06abb997b6ccd1f6e93af8e2f673f25c736c6ccfbd",
      "kind": "transparent"
    },
    {
      "address": "0x27efa1C90e097c980c669AB1a6e326AD4164f1Cb",
      "txHash": "0xaf69592d6d0de413dc34ee70a7cd84c546003c8b4cda7af36a33d2dfb76f93e0",
      "kind": "transparent"
    },
    {
      "address": "0x8AdFcF226dfb2fA73788Ad711C958Ba251369cb3",
      "txHash": "0x01bb67ef35a27c1ca2671a9d414f89d9b95466ea345d004a037366e6dfcb7246",
      "kind": "transparent"
    },
    {
      "address": "0xc6B90f42Ea395898B4C1B33e5C8Fa351829BCD90",
      "txHash": "0xaf237f23750a6de866021273380e81f3ad43e79efd94dd58ca934a34ec21537e",
      "kind": "transparent"
    },
    {
      "address": "0x0c33c9dEF7A3d9961b802C6C6402d306b7D48135",
      "txHash": "0x7c92bccb949faaeec6f903514aac0f690be02ecf9a980bdfeaa789722e11af26",
      "kind": "transparent"
    }
  ],
  "impls": {
    "094d8f3a0bf92c7d9dd1bcf3e1993ce604a860205623927e1b22ede5fe9c4c4c": {
      "address": "0x5C5E2D94b107C7691B08E43169fDe76EAAB6D48b",
      "txHash": "0x349528fa9e7975dd0c8b3685aff88c4d10450656ba9d33abd610044def3cf0df",
      "layout": {
        "solcVersion": "0.8.17",
        "storage": [
          {
            "label": "_initialized",
            "offset": 0,
            "slot": "0",
            "type": "t_uint8",
            "contract": "Initializable",
            "src": "@openzeppelin/contracts-upgradeable/proxy/utils/Initializable.sol:62",
            "retypedFrom": "bool"
          },
          {
            "label": "_initializing",
            "offset": 1,
            "slot": "0",
            "type": "t_bool",
            "contract": "Initializable",
            "src": "@openzeppelin/contracts-upgradeable/proxy/utils/Initializable.sol:67"
          },
          {
            "label": "projectsCount",
            "offset": 0,
            "slot": "1",
            "type": "t_uint256",
            "contract": "ProjectRegistry",
            "src": "contracts/projectRegistry/ProjectRegistry.sol:43"
          },
          {
            "label": "projects",
            "offset": 0,
            "slot": "2",
            "type": "t_mapping(t_uint256,t_struct(Project)8513_storage)",
            "contract": "ProjectRegistry",
            "src": "contracts/projectRegistry/ProjectRegistry.sol:46"
          },
          {
            "label": "projectsOwners",
            "offset": 0,
            "slot": "3",
            "type": "t_mapping(t_uint256,t_struct(OwnerList)8520_storage)",
            "contract": "ProjectRegistry",
            "src": "contracts/projectRegistry/ProjectRegistry.sol:49"
          }
        ],
        "types": {
          "t_address": {
            "label": "address",
            "numberOfBytes": "20"
          },
          "t_bool": {
            "label": "bool",
            "numberOfBytes": "1"
          },
          "t_mapping(t_address,t_address)": {
            "label": "mapping(address => address)",
            "numberOfBytes": "32"
          },
          "t_mapping(t_uint256,t_struct(OwnerList)8520_storage)": {
            "label": "mapping(uint256 => struct ProjectRegistry.OwnerList)",
            "numberOfBytes": "32"
          },
          "t_mapping(t_uint256,t_struct(Project)8513_storage)": {
            "label": "mapping(uint256 => struct ProjectRegistry.Project)",
            "numberOfBytes": "32"
          },
          "t_string_storage": {
            "label": "string",
            "numberOfBytes": "32"
          },
          "t_struct(MetaPtr)10513_storage": {
            "label": "struct MetaPtr",
            "members": [
              {
                "label": "protocol",
                "type": "t_uint256",
                "offset": 0,
                "slot": "0"
              },
              {
                "label": "pointer",
                "type": "t_string_storage",
                "offset": 0,
                "slot": "1"
              }
            ],
            "numberOfBytes": "64"
          },
          "t_struct(OwnerList)8520_storage": {
            "label": "struct ProjectRegistry.OwnerList",
            "members": [
              {
                "label": "count",
                "type": "t_uint256",
                "offset": 0,
                "slot": "0"
              },
              {
                "label": "list",
                "type": "t_mapping(t_address,t_address)",
                "offset": 0,
                "slot": "1"
              }
            ],
            "numberOfBytes": "64"
          },
          "t_struct(Project)8513_storage": {
            "label": "struct ProjectRegistry.Project",
            "members": [
              {
                "label": "id",
                "type": "t_uint256",
                "offset": 0,
                "slot": "0"
              },
              {
                "label": "metadata",
                "type": "t_struct(MetaPtr)10513_storage",
                "offset": 0,
                "slot": "1"
              }
            ],
            "numberOfBytes": "96"
          },
          "t_uint256": {
            "label": "uint256",
            "numberOfBytes": "32"
          },
          "t_uint8": {
            "label": "uint8",
            "numberOfBytes": "1"
          }
        }
      }
    },
    "d6cad864bee7d4183f11eb60bc8562f63cd064dd64ceb0cd5eb28937afefa981": {
      "address": "0x424C5C175fbd46CA0b27866044A5B956c6AbEe0D",
      "txHash": "0x7821e4f7952e3985f83e264c32f7c183de0574f184de20ab4cc5c57226878981",
      "layout": {
        "solcVersion": "0.8.17",
        "storage": [
          {
            "label": "_initialized",
            "offset": 0,
            "slot": "0",
            "type": "t_uint8",
            "contract": "Initializable",
            "src": "@openzeppelin/contracts-upgradeable/proxy/utils/Initializable.sol:62",
            "retypedFrom": "bool"
          },
          {
            "label": "_initializing",
            "offset": 1,
            "slot": "0",
            "type": "t_bool",
            "contract": "Initializable",
            "src": "@openzeppelin/contracts-upgradeable/proxy/utils/Initializable.sol:67"
          },
          {
            "label": "__gap",
            "offset": 0,
            "slot": "1",
            "type": "t_array(t_uint256)50_storage",
            "contract": "ContextUpgradeable",
            "src": "@openzeppelin/contracts-upgradeable/utils/ContextUpgradeable.sol:36"
          },
          {
            "label": "_owner",
            "offset": 0,
            "slot": "51",
            "type": "t_address",
            "contract": "OwnableUpgradeable",
            "src": "@openzeppelin/contracts-upgradeable/access/OwnableUpgradeable.sol:22"
          },
          {
            "label": "__gap",
            "offset": 0,
            "slot": "52",
            "type": "t_array(t_uint256)49_storage",
            "contract": "OwnableUpgradeable",
            "src": "@openzeppelin/contracts-upgradeable/access/OwnableUpgradeable.sol:94"
          },
          {
            "label": "programContract",
            "offset": 0,
            "slot": "101",
            "type": "t_address",
            "contract": "ProgramFactory",
            "src": "contracts/program/ProgramFactory.sol:12"
          }
        ],
        "types": {
          "t_address": {
            "label": "address",
            "numberOfBytes": "20"
          },
          "t_array(t_uint256)49_storage": {
            "label": "uint256[49]",
            "numberOfBytes": "1568"
          },
          "t_array(t_uint256)50_storage": {
            "label": "uint256[50]",
            "numberOfBytes": "1600"
          },
          "t_bool": {
            "label": "bool",
            "numberOfBytes": "1"
          },
          "t_uint256": {
            "label": "uint256",
            "numberOfBytes": "32"
          },
          "t_uint8": {
            "label": "uint8",
            "numberOfBytes": "1"
          }
        }
      }
    },
    "85fb214ebcdd584f44a6a82b623ca8dffe10d1c30090a42c2e97c3c604622e01": {
      "address": "0x545B282A50EaeA01A619914d44105437036CbB36",
      "txHash": "0xfc4e430cb8da1b8c6e8ea4187696e5d1db197d617e4c8fa53e97243f620a27e6",
      "layout": {
        "solcVersion": "0.8.17",
        "storage": [
          {
            "label": "_initialized",
            "offset": 0,
            "slot": "0",
            "type": "t_uint8",
            "contract": "Initializable",
            "src": "@openzeppelin/contracts-upgradeable/proxy/utils/Initializable.sol:62",
            "retypedFrom": "bool"
          },
          {
            "label": "_initializing",
            "offset": 1,
            "slot": "0",
            "type": "t_bool",
            "contract": "Initializable",
            "src": "@openzeppelin/contracts-upgradeable/proxy/utils/Initializable.sol:67"
          },
          {
            "label": "__gap",
            "offset": 0,
            "slot": "1",
            "type": "t_array(t_uint256)50_storage",
            "contract": "ContextUpgradeable",
            "src": "@openzeppelin/contracts-upgradeable/utils/ContextUpgradeable.sol:36"
          },
          {
            "label": "_owner",
            "offset": 0,
            "slot": "51",
            "type": "t_address",
            "contract": "OwnableUpgradeable",
            "src": "@openzeppelin/contracts-upgradeable/access/OwnableUpgradeable.sol:22"
          },
          {
            "label": "__gap",
            "offset": 0,
            "slot": "52",
            "type": "t_array(t_uint256)49_storage",
            "contract": "OwnableUpgradeable",
            "src": "@openzeppelin/contracts-upgradeable/access/OwnableUpgradeable.sol:94"
          },
          {
            "label": "votingContract",
            "offset": 0,
            "slot": "101",
            "type": "t_address",
            "contract": "QuadraticFundingVotingStrategyFactory",
            "src": "contracts/votingStrategy/QuadraticFundingStrategy/QuadraticFundingVotingStrategyFactory.sol:13"
          },
          {
            "label": "nonce",
            "offset": 0,
            "slot": "102",
            "type": "t_uint256",
            "contract": "QuadraticFundingVotingStrategyFactory",
            "src": "contracts/votingStrategy/QuadraticFundingStrategy/QuadraticFundingVotingStrategyFactory.sol:15"
          }
        ],
        "types": {
          "t_address": {
            "label": "address",
            "numberOfBytes": "20"
          },
          "t_array(t_uint256)49_storage": {
            "label": "uint256[49]",
            "numberOfBytes": "1568"
          },
          "t_array(t_uint256)50_storage": {
            "label": "uint256[50]",
            "numberOfBytes": "1600"
          },
          "t_bool": {
            "label": "bool",
            "numberOfBytes": "1"
          },
          "t_uint256": {
            "label": "uint256",
            "numberOfBytes": "32"
          },
          "t_uint8": {
            "label": "uint8",
            "numberOfBytes": "1"
          }
        }
      }
    },
    "a36cf49fd516c08806a27c0b932fd0ea57d0980e0d2acc596776c2292d83a9cf": {
      "address": "0x5b55728e41154562ee80027C1247B13382692e5C",
      "txHash": "0x824a5edc44ecb62d063bf2c969b11020db31db79f91d56f3ee3cef989cdf8eb6",
      "layout": {
        "solcVersion": "0.8.17",
        "storage": [
          {
            "label": "_initialized",
            "offset": 0,
            "slot": "0",
            "type": "t_uint8",
            "contract": "Initializable",
            "src": "@openzeppelin/contracts-upgradeable/proxy/utils/Initializable.sol:62",
            "retypedFrom": "bool"
          },
          {
            "label": "_initializing",
            "offset": 1,
            "slot": "0",
            "type": "t_bool",
            "contract": "Initializable",
            "src": "@openzeppelin/contracts-upgradeable/proxy/utils/Initializable.sol:67"
          },
          {
            "label": "__gap",
            "offset": 0,
            "slot": "1",
            "type": "t_array(t_uint256)50_storage",
            "contract": "ContextUpgradeable",
            "src": "@openzeppelin/contracts-upgradeable/utils/ContextUpgradeable.sol:36"
          },
          {
            "label": "_owner",
            "offset": 0,
            "slot": "51",
            "type": "t_address",
            "contract": "OwnableUpgradeable",
            "src": "@openzeppelin/contracts-upgradeable/access/OwnableUpgradeable.sol:22"
          },
          {
            "label": "__gap",
            "offset": 0,
            "slot": "52",
            "type": "t_array(t_uint256)49_storage",
            "contract": "OwnableUpgradeable",
            "src": "@openzeppelin/contracts-upgradeable/access/OwnableUpgradeable.sol:94"
          },
          {
            "label": "payoutImplementation",
            "offset": 0,
            "slot": "101",
            "type": "t_address_payable",
            "contract": "MerklePayoutStrategyFactory",
            "src": "contracts/payoutStrategy/MerklePayoutStrategy/MerklePayoutStrategyFactory.sol:15"
          },
          {
            "label": "nonce",
            "offset": 0,
            "slot": "102",
            "type": "t_uint256",
            "contract": "MerklePayoutStrategyFactory",
            "src": "contracts/payoutStrategy/MerklePayoutStrategy/MerklePayoutStrategyFactory.sol:17"
          }
        ],
        "types": {
          "t_address": {
            "label": "address",
            "numberOfBytes": "20"
          },
          "t_address_payable": {
            "label": "address payable",
            "numberOfBytes": "20"
          },
          "t_array(t_uint256)49_storage": {
            "label": "uint256[49]",
            "numberOfBytes": "1568"
          },
          "t_array(t_uint256)50_storage": {
            "label": "uint256[50]",
            "numberOfBytes": "1600"
          },
          "t_bool": {
            "label": "bool",
            "numberOfBytes": "1"
          },
          "t_uint256": {
            "label": "uint256",
            "numberOfBytes": "32"
          },
          "t_uint8": {
            "label": "uint8",
            "numberOfBytes": "1"
          }
        }
      }
    },
    "96865c174eef7f8315380a3ef530172be2dda3472c66e8976749ea6c77eaa870": {
      "address": "0x74c3665540FC8B92Dd06a7e56a51eCa038C18180",
      "txHash": "0xd509add6d586dba48da4568aacacf26a9ed01694eab76f2847c18e5d4c36554b",
      "layout": {
        "solcVersion": "0.8.17",
        "storage": [
          {
            "label": "_initialized",
            "offset": 0,
            "slot": "0",
            "type": "t_uint8",
            "contract": "Initializable",
            "src": "@openzeppelin/contracts-upgradeable/proxy/utils/Initializable.sol:62",
            "retypedFrom": "bool"
          },
          {
            "label": "_initializing",
            "offset": 1,
            "slot": "0",
            "type": "t_bool",
            "contract": "Initializable",
            "src": "@openzeppelin/contracts-upgradeable/proxy/utils/Initializable.sol:67"
          },
          {
            "label": "__gap",
            "offset": 0,
            "slot": "1",
            "type": "t_array(t_uint256)50_storage",
            "contract": "ContextUpgradeable",
            "src": "@openzeppelin/contracts-upgradeable/utils/ContextUpgradeable.sol:36"
          },
          {
            "label": "_owner",
            "offset": 0,
            "slot": "51",
            "type": "t_address",
            "contract": "OwnableUpgradeable",
            "src": "@openzeppelin/contracts-upgradeable/access/OwnableUpgradeable.sol:22"
          },
          {
            "label": "__gap",
            "offset": 0,
            "slot": "52",
            "type": "t_array(t_uint256)49_storage",
            "contract": "OwnableUpgradeable",
            "src": "@openzeppelin/contracts-upgradeable/access/OwnableUpgradeable.sol:94"
          },
          {
            "label": "roundImplementation",
            "offset": 0,
            "slot": "101",
            "type": "t_address",
            "contract": "RoundFactory",
            "src": "contracts/round/RoundFactory.sol:30"
          },
          {
            "label": "alloSettings",
            "offset": 0,
            "slot": "102",
            "type": "t_address",
            "contract": "RoundFactory",
            "src": "contracts/round/RoundFactory.sol:33"
          },
          {
            "label": "nonce",
            "offset": 0,
            "slot": "103",
            "type": "t_uint256",
            "contract": "RoundFactory",
            "src": "contracts/round/RoundFactory.sol:36"
          }
        ],
        "types": {
          "t_address": {
            "label": "address",
            "numberOfBytes": "20"
          },
          "t_array(t_uint256)49_storage": {
            "label": "uint256[49]",
            "numberOfBytes": "1568"
          },
          "t_array(t_uint256)50_storage": {
            "label": "uint256[50]",
            "numberOfBytes": "1600"
          },
          "t_bool": {
            "label": "bool",
            "numberOfBytes": "1"
          },
          "t_uint256": {
            "label": "uint256",
            "numberOfBytes": "32"
          },
          "t_uint8": {
            "label": "uint8",
            "numberOfBytes": "1"
          }
        }
      }
    },
    "777deeff9d03cd6e376d1feca8a0c01b6bf75339df9cacbb788c98f548a864e6": {
      "address": "0x7ac74Be34b1A27E48a2525259719F877a57B2Aa4",
      "txHash": "0x7360fac495fdacf876b127e3d6ec600cd7e9e0f469273966471fd2507840c558",
      "layout": {
        "solcVersion": "0.8.17",
        "storage": [
          {
            "label": "_initialized",
            "offset": 0,
            "slot": "0",
            "type": "t_uint8",
            "contract": "Initializable",
            "src": "@openzeppelin/contracts-upgradeable/proxy/utils/Initializable.sol:62",
            "retypedFrom": "bool"
          },
          {
            "label": "_initializing",
            "offset": 1,
            "slot": "0",
            "type": "t_bool",
            "contract": "Initializable",
            "src": "@openzeppelin/contracts-upgradeable/proxy/utils/Initializable.sol:67"
          },
          {
            "label": "__gap",
            "offset": 0,
            "slot": "1",
            "type": "t_array(t_uint256)50_storage",
            "contract": "ContextUpgradeable",
            "src": "@openzeppelin/contracts-upgradeable/utils/ContextUpgradeable.sol:36"
          },
          {
            "label": "_owner",
            "offset": 0,
            "slot": "51",
            "type": "t_address",
            "contract": "OwnableUpgradeable",
            "src": "@openzeppelin/contracts-upgradeable/access/OwnableUpgradeable.sol:22"
          },
          {
            "label": "__gap",
            "offset": 0,
            "slot": "52",
            "type": "t_array(t_uint256)49_storage",
            "contract": "OwnableUpgradeable",
            "src": "@openzeppelin/contracts-upgradeable/access/OwnableUpgradeable.sol:94"
          },
          {
            "label": "protocolTreasury",
            "offset": 0,
            "slot": "101",
            "type": "t_address_payable",
            "contract": "AlloSettings",
            "src": "contracts/settings/AlloSettings.sol:16"
          },
          {
            "label": "protocolFeePercentage",
            "offset": 20,
            "slot": "101",
            "type": "t_uint24",
            "contract": "AlloSettings",
            "src": "contracts/settings/AlloSettings.sol:20"
          }
        ],
        "types": {
          "t_address": {
            "label": "address",
            "numberOfBytes": "20"
          },
          "t_address_payable": {
            "label": "address payable",
            "numberOfBytes": "20"
          },
          "t_array(t_uint256)49_storage": {
            "label": "uint256[49]",
            "numberOfBytes": "1568"
          },
          "t_array(t_uint256)50_storage": {
            "label": "uint256[50]",
            "numberOfBytes": "1600"
          },
          "t_bool": {
            "label": "bool",
            "numberOfBytes": "1"
          },
          "t_uint24": {
            "label": "uint24",
            "numberOfBytes": "3"
          },
          "t_uint256": {
            "label": "uint256",
            "numberOfBytes": "32"
          },
          "t_uint8": {
            "label": "uint8",
            "numberOfBytes": "1"
          }
        }
      }
    }
  }
}
